langchain_clickzetta/__init__.py
langchain_clickzetta/chat_message_histories.py
langchain_clickzetta/engine.py
langchain_clickzetta/hybrid_store.py
langchain_clickzetta/retrievers.py
langchain_clickzetta/sql_chain.py
langchain_clickzetta/stores.py
langchain_clickzetta/vectorstores.py
langchain_clickzetta/volume_store.py
langchain_clickzetta-0.1.15.dist-info/METADATA
langchain_clickzetta-0.1.15.dist-info/WHEEL
langchain_clickzetta-0.1.15.dist-info/licenses/LICENSE
langchain_clickzetta-0.1.15.dist-info/RECORD
