Metadata-Version: 2.4
Name: langchain-clickzetta
Version: 0.1.15
Summary: An integration package connecting ClickZetta and LangChain
Author-email: ClickZetta LangChain Integration Team <support@clickzetta.com>
License: MIT
License-File: LICENSE
Keywords: clickzetta,embeddings,full-text-search,langchain,llm,sql,vector-database
Classifier: Development Status :: 4 - Beta
Classifier: Intended Audience :: Developers
Classifier: License :: OSI Approved :: MIT License
Classifier: Programming Language :: Python :: 3
Classifier: Programming Language :: Python :: 3.9
Classifier: Programming Language :: Python :: 3.10
Classifier: Programming Language :: Python :: 3.11
Classifier: Topic :: Database
Classifier: Topic :: Scientific/Engineering :: Artificial Intelligence
Classifier: Topic :: Software Development :: Libraries :: Python Modules
Requires-Python: >=3.9
Requires-Dist: clickzetta-connector-python>=0.8.92
Requires-Dist: clickzetta-zettapark-python>=0.1.3
Requires-Dist: langchain-core>=0.1.0
Requires-Dist: numpy>=1.20.0
Requires-Dist: pydantic>=2.0.0
Requires-Dist: sqlalchemy>=2.0.0
Requires-Dist: typing-extensions>=4.0.0
Provides-Extra: all
Requires-Dist: pandas>=2.0.0; extra == 'all'
Provides-Extra: dataframe
Requires-Dist: pandas>=2.0.0; extra == 'dataframe'
Provides-Extra: dev
Requires-Dist: black>=23.0.0; extra == 'dev'
Requires-Dist: mypy>=1.0.0; extra == 'dev'
Requires-Dist: pandas>=2.0.0; extra == 'dev'
Requires-Dist: pytest-asyncio>=0.21.0; extra == 'dev'
Requires-Dist: pytest-cov>=4.0.0; extra == 'dev'
Requires-Dist: pytest-mock>=3.10.0; extra == 'dev'
Requires-Dist: pytest>=7.0.0; extra == 'dev'
Requires-Dist: ruff>=0.1.0; extra == 'dev'
Provides-Extra: lint
Requires-Dist: black>=23.0.0; extra == 'lint'
Requires-Dist: mypy>=1.0.0; extra == 'lint'
Requires-Dist: ruff>=0.1.0; extra == 'lint'
Provides-Extra: test
Requires-Dist: pytest-asyncio>=0.21.0; extra == 'test'
Requires-Dist: pytest-cov>=4.0.0; extra == 'test'
Requires-Dist: pytest-mock>=3.10.0; extra == 'test'
Requires-Dist: pytest>=7.0.0; extra == 'test'
